firebase_cart/__init__.py
firebase_cart/cart.py
firebase_cart/database.py
firebase_cart/logging.py
firebase_cart/models.py
firebase_cart/order.py
firebase_cart/utils.py
firebase_cart-0.1.1.dist-info/METADATA
firebase_cart-0.1.1.dist-info/WHEEL
firebase_cart-0.1.1.dist-info/top_level.txt
firebase_cart-0.1.1.dist-info/RECORD
