Metadata-Version: 2.1
Name: firebase_cart
Version: 0.1.1
Summary: A Firebase-based cart package for Python applications
Author-email: Adeniyi Aderounm <teebarg01@gmail.com>
Project-URL: Homepage, https://github.com/teebarg/firebase_cart
Project-URL: Bug Tracker, https://github.com/teebarg/firebase_cart/issues
Classifier: Programming Language :: Python :: 3
Classifier: License :: OSI Approved :: MIT License
Classifier: Operating System :: OS Independent
Requires-Python: >=3.7
Requires-Dist: firebase-admin ==6.4.0
Requires-Dist: pydantic ==2.8.2
